pybond/__init__.py
pybond/assertions.py
pybond/james.py
pybond/memory.py
pybond/types.py
pybond/util.py
pybond-0.2.2.dist-info/METADATA
pybond-0.2.2.dist-info/WHEEL
pybond-0.2.2.dist-info/RECORD
