Metadata-Version: 2.1
Name: pybond
Version: 0.2.2
Summary: pybond is a spying and stubbing library inspired by the clojure bond library.
Home-page: https://github.com/epgui/pybond
License: Eclipse Public License - v 1.0
Keywords: bond,monkeypatch,spy,stub,clojure,functional programming
Author: Guillaume Pelletier
Author-email: guigui.p@gmail.com
Requires-Python: >=3.10,<4.0
Classifier: Intended Audience :: Developers
Classifier: License :: Other/Proprietary License
Classifier: Operating System :: OS Independent
Classifier: Programming Language :: Python :: 3
Classifier: Programming Language :: Python :: 3.10
Classifier: Programming Language :: Python :: 3.11
Classifier: Programming Language :: Python :: 3.12
Classifier: Topic :: Software Development :: Libraries
Classifier: Topic :: Software Development :: Testing
Classifier: Topic :: Utilities
Project-URL: Repository, https://github.com/epgui/pybond
